{"script_txt": [{"tipo": "SHOW"}, {"tipo": "TALK_IN"}, {"tipo": "BG_LOAD", "clase": "FADE_IN", "nombre": "hime_nc007a", "time": 2.0, "x_scal": 1.25, "y_scal": 0.938}, {"tipo": "BGM_PLAY", "volumen": 0.5, "nombre": "snd_bgm_e_story_002", "extension": ".ogg"}, {"tipo": "CHAR_TALK", "nombre": "", "texto": "Despu\u00e9s de una misi\u00f3n, est\u00e1bamos en una posada cercana al lugar de la misi\u00f3n."}, {"tipo": "CHAR_TALK", "nombre": "", "texto": "Nuestro regreso a Gosha se retras\u00f3 para el d\u00eda siguiente, porque la misi\u00f3n tom\u00f3 m\u00e1s tiempo de lo esperado ."}, {"tipo": "VOICE_PLAY", "voz1": "voi_favor_s042_ore_0000", "voz2": ""}, {"tipo": "CHAR_TALK", "nombre": "Fuuma", "texto": "Quer\u00eda volver inmediatamente despu\u00e9s de la misi\u00f3n ......"}, {"tipo": "CHAR_TALK", "nombre_char": "spika", "x_pos": 0.0, "y_pos": "-140", "nombre_image": "supporter_042_0"}, {"tipo": "CHAR_SCALE", "nombre_char": "spika", "escala": 1.1}, {"tipo": "CHAR_FADE", "nombre_char": "spika", "tipo_fade": "FADE_IN", "x_pos": 0.0, "time": 0.2}, {"tipo": "VOICE_PLAY", "voz1": "voi_favor_s042_supika_0000", "voz2": ""}, {"tipo": "CHAR_TALK", "nombre": "Spica", "texto": "De verdad?\u00a0Me gusta pasar una noche en posadas con \"buena vibra\" ~"}, {"tipo": "CHAR_TALK", "nombre": "", "texto": "La dama que parece feliz es una inspectora de la UFS que acompa\u00f1\u00f3 esta misi\u00f3n, Kuonji R. Spica."}, {"tipo": "CHAR_TALK", "nombre": "", "texto": "Ella es un ser peculiar, ya que lucha a cualquier distancia, usando una pistola y una katana. Su madre tambi\u00e9n era una Taimanin, por lo que tambi\u00e9n es capaz de usar artes ninja."}, {"tipo": "CHAR_TALK", "nombre": "", "texto": "Adem\u00e1s de eso, parece que le gustan los elementos del per\u00edodo de los Estados en guerra en Jap\u00f3n, incluso cuando es de la UFS, porque parec\u00eda emocionada con el estilo japon\u00e9s interior de la posada."}, {"tipo": "VOICE_PLAY", "voz1": "voi_favor_s042_supika_0001", "voz2": ""}, {"tipo": "CHAR_TALK", "nombre": "Spica", "texto": "Hola, capit\u00e1n ~ \u00a1 El posadero dijo que hay un festival de\u00a0verano\u00a0abierto cerca!\u00a0Vamos a verlo ~"}, {"tipo": "VOICE_PLAY", "voz1": "voi_favor_s042_ore_0001", "voz2": ""}, {"tipo": "CHAR_TALK", "nombre": "Fuuma", "texto": "Esa persona es un empleado, no el posadero.\u00a0Pareces muy en\u00e9rgica, acabamos de terminar la misi\u00f3n ... \u00bfNo crees que va a estar lleno?"}, {"tipo": "VOICE_PLAY", "voz1": "voi_favor_s042_supika_0002", "voz2": ""}, {"tipo": "CHAR_TALK", "nombre": "Spica", "texto": "\u00bfAcaso no es ese el objetivo de un festival?\u00a0Se supone que debe estar lleno. Adem\u00e1s, ma\u00f1ana es feriado y nos dejar\u00e1n usar una yukata. No tendr\u00e1s muchas oportunidades como esta, sabes ~."}, {"tipo": "VOICE_PLAY", "voz1": "voi_favor_s042_ore_0002", "voz2": ""}, {"tipo": "CHAR_TALK", "nombre": "Fuuma", "texto": "Bueno, no te equivocas pero ..."}, {"tipo": "CHAR_TALK", "nombre": "", "texto": "Spica es un poco mayor que yo, pero act\u00faa como si fuera m\u00e1s joven."}, {"tipo": "CHAR_TALK", "nombre": "", "texto": "Para ser honesto, s\u00ed quer\u00eda ir y divertirme mucho, as\u00ed que no pude negarme de inmediato."}, {"tipo": "CHAR_TALK", "nombre": "", "texto": "Spica probablemente pudo ver que yo tambi\u00e9n quer\u00eda ir, as\u00ed que continu\u00f3 persuadi\u00e9ndome."}, {"tipo": "VOICE_PLAY", "voz1": "voi_favor_s042_supika_0003", "voz2": ""}, {"tipo": "CHAR_TALK", "nombre": "Spica", "texto": "Mira, s\u00e9 que t\u00fa tambi\u00e9n quieres ir, \u00a1Se te ve en toda la cara! S\u00f3lo somos t\u00fa y yo, te arrepentir\u00e1s si no vas."}, {"tipo": "VOICE_PLAY", "voz1": "voi_favor_s042_ore_0003", "voz2": ""}, {"tipo": "CHAR_TALK", "nombre": "Fuuma", "texto": "Supongo que s\u00ed.\u00a0Pasamos mucho tiempo en la misi\u00f3n y necesitamos un poco de tiempo para relajarnos."}, {"tipo": "CHAR_TALK", "nombre": "", "texto": "El rostro de Spica se ilumin\u00f3 cuando me rend\u00ed y asent\u00ed en aceptaci\u00f3n."}, {"tipo": "VOICE_PLAY", "voz1": "voi_favor_s042_supika_0004", "voz2": ""}, {"tipo": "CHAR_TALK", "nombre": "Spica", "texto": "\u00a1Si!\u00a0bueno, est\u00e1 decidido, \u00a1as\u00ed que les voy a pedir que me ayuden a vestirme en mi yukata!"}, {"tipo": "SE_PLAY", "volumen": 1.0, "nombre": "snd_story_run01", "loop": "SE", "extension": ".ogg"}, {"tipo": "MOVE_TO", "nombre_char": "spika", "x_pos": 6.0, "time": 0.0}, {"tipo": "CHAR_FADE", "nombre_char": "spika", "tipo_fade": "FADE_OUT", "x_pos": 6.0, "time": 0.2}, {"tipo": "CHAR_TALK", "nombre": "", "texto": "Spica sali\u00f3 corriendo de la habitaci\u00f3n, emocionada."}, {"tipo": "VOICE_PLAY", "voz1": "voi_favor_s042_ore_0004", "voz2": ""}, {"tipo": "CHAR_TALK", "nombre": "Fuuma", "texto": "Supongo que estar\u00e1 bien si est\u00e1 tan emocionada."}, {"tipo": "CHAR_TALK", "nombre": "", "texto": "Murmur\u00e9, pero tambi\u00e9n estaba empezando a emocionarme, ahora que hab\u00eda aceptado ir."}, {"tipo": "VOICE_PLAY", "voz1": "voi_favor_s042_ore_0005", "voz2": ""}, {"tipo": "CHAR_TALK", "nombre": "Fuuma", "texto": "\u00a1Supongo que yo tambi\u00e9n me ten\u00eda que ir a preparar!"}, {"tipo": "CHAR_TALK", "nombre": "", "texto": "Me apresur\u00e9 y fui tras Spica."}, {"tipo": "BG_LOAD", "clase": "MOVE", "nombre": "supporter_042_0", "time": 1.5, "x_scal": 1.0, "y_scal": 1.0, "efecto": "LEFT_RIGHT"}, {"tipo": "VOICE_PLAY", "voz1": "voi_favor_s042_supika_0005", "voz2": ""}, {"tipo": "CHAR_TALK", "nombre": "Spica", "texto": "\u00a1Ooh ~!\u00a0\u00a1Este es un festival japon\u00e9s leg\u00edtimo!\u00a0\u00a1Incre\u00edble!\u00a0\u00a1Esto es tan genial!"}, {"tipo": "CHAR_TALK", "nombre": "", "texto": "Spica grit\u00f3 como una ni\u00f1a extasiada en su yukata."}, {"tipo": "VOICE_PLAY", "voz1": "voi_favor_s042_ore_0006", "voz2": ""}, {"tipo": "CHAR_TALK", "nombre": "Fuuma", "texto": "Este festival es mejor de lo que pensaba.\u00a0\u00a1Mira todas las tiendas!"}, {"tipo": "VOICE_PLAY", "voz1": "voi_favor_s042_supika_0006", "voz2": ""}, {"tipo": "CHAR_TALK", "nombre": "Spica", "texto": "\u00bfOh si?\u00a0Entonces tuvimos mucha suerte ~ \u266a Incluso usamos una linda yukata como esta, ser\u00eda una pena si el festival hubiera sido una decepci\u00f3n ~"}, {"tipo": "CHAR_TALK", "nombre": "", "texto": "Spica agit\u00f3 las mangas de su yukata como un p\u00e1jaro mientras hablaba."}, {"tipo": "CHAR_TALK", "nombre": "", "texto": "Es muy diferente a lo que usaba normalmente, pero le quedaba bien."}, {"tipo": "VOICE_PLAY", "voz1": "voi_favor_s042_supika_0007", "voz2": ""}, {"tipo": "CHAR_TALK", "nombre": "Spica", "texto": "\u00a1Oooh ~, siempre hab\u00eda so\u00f1ado con usar un kimono! \u00a1Estaba deseando ta~nto que llegara el momento desde que supe que iba a venir Jap\u00f3n!"}, {"tipo": "VOICE_PLAY", "voz1": "voi_favor_s042_ore_0007", "voz2": ""}, {"tipo": "CHAR_TALK", "nombre": "Fuuma", "texto": "\u00a1Esta es un yukata de muy buena calidad!\u00a0Incluso tiene bonitos obi (fajas)."}, {"tipo": "VOICE_PLAY", "voz1": "voi_favor_s042_supika_0008", "voz2": ""}, {"tipo": "CHAR_TALK", "nombre": "Spica", "texto": "\u00bfOh si?\u00a0A s\u00ed parece.\u00a0Es muy colorido y no hay agujeros en la tela, por lo que es bonito y lindo \u266a"}, {"tipo": "CHAR_TALK", "nombre": "", "texto": "Deb\u00eda estar muy feliz, porque segu\u00eda girando."}, {"tipo": "CHAR_TALK", "nombre": "", "texto": "A su alrededor, burbujas comenzaron a flotar y comenzaron a brillar."}, {"tipo": "VOICE_PLAY", "voz1": "voi_favor_s042_ore_0008", "voz2": ""}, {"tipo": "CHAR_TALK", "nombre": "Fuuma", "texto": "\u00bfHmm?\u00a0Spica?\u00a0\u00bfEn d\u00f3nde conseguiste burbujas?"}, {"tipo": "VOICE_PLAY", "voz1": "voi_favor_s042_supika_0009", "voz2": ""}, {"tipo": "CHAR_TALK", "nombre": "Spica", "texto": "No las compr\u00e9, es mi arte ninja ~ Estoy usando una yukata, as\u00ed que ser\u00eda un desperdicio no intentar esto. \u00bfQu\u00e9 piensas?\u00a0\u00bfMe veo linda ~?"}, {"tipo": "CHAR_TALK", "nombre": "", "texto": "Me sobresalt\u00e9 cuando Spica se acerc\u00f3 a m\u00ed."}, {"tipo": "VOICE_PLAY", "voz1": "voi_favor_s042_ore_0009", "voz2": ""}, {"tipo": "CHAR_TALK", "nombre": "Fuuma", "texto": "\u00a1Lo s\u00e9, pero usar tu arte ninja en un lugar lleno de gente como este es \u2026\u2026!"}, {"tipo": "VOICE_PLAY", "voz1": "voi_favor_s042_supika_0010", "voz2": ""}, {"tipo": "CHAR_TALK", "nombre": "Spica", "texto": "Oh, vamos ~ Si una chica se ve bonita y linda, \u00a1Se supone que deber\u00edas darle cumplidos !\u00a0\u00a1Qu\u00e9 pocos modales!\u00a0\u00a1Qu\u00e9 poco sofisticado!"}, {"tipo": "VOICE_PLAY", "voz1": "voi_favor_s042_ore_0010", "voz2": ""}, {"tipo": "CHAR_TALK", "nombre": "Fuuma", "texto": "No tienes que exagerar tanto ..."}, {"tipo": "CHAR_TALK", "nombre": "", "texto": "Era linda y todo eso, pero es vergonzoso decir ese tipo de cosas con toda esta gente alrededor."}, {"tipo": "CHAR_TALK", "nombre": "", "texto": "Intent\u00e9 cambiar de tema, pero Spica, encontr\u00f3 mis reacci\u00f3n entretenida y se acerc\u00f3 a m\u00ed."}, {"tipo": "VOICE_PLAY", "voz1": "voi_favor_s042_supika_0011", "voz2": ""}, {"tipo": "CHAR_TALK", "nombre": "Spica", "texto": "Dime si no me queda bien por favor ... Ya me prepar\u00e9."}, {"tipo": "VOICE_PLAY", "voz1": "voi_favor_s042_ore_0011", "voz2": ""}, {"tipo": "CHAR_TALK", "nombre": "Fuuma", "texto": "\u00a1Nunca dije que no te queda bien! S\u00ed te queda muy bien y est\u00e1 linda..."}, {"tipo": "CHAR_TALK", "nombre": "", "texto": "No s\u00e9 si estaba copiando una l\u00ednea de un drama hist\u00f3rico o algo as\u00ed, pero cuando lo dijo as\u00ed, me confund\u00ed."}, {"tipo": "CHAR_TALK", "nombre": "", "texto": "Apart\u00e9 la mirada y le susurr\u00e9, pero no parec\u00eda querer escucharlo as\u00ed."}, {"tipo": "VOICE_PLAY", "voz1": "voi_favor_s042_supika_0012", "voz2": ""}, {"tipo": "CHAR_TALK", "nombre": "Spica", "texto": "\u00bfQu\u00e9?\u00a0\u00bfQu\u00e9?\u00a0\u00bfQu\u00e9 dijiste?\u00a0\u00bfNo puedo escucharte ~?"}, {"tipo": "CHAR_TALK", "nombre": "", "texto": "Spica estaba tratando de enfrentarme y mirarme directamente a la cara. Claramente estaba disfrutando este momento."}, {"tipo": "VOICE_PLAY", "voz1": "voi_favor_s042_supika_0013", "voz2": ""}, {"tipo": "CHAR_TALK", "nombre": "Spica", "texto": "Vamos ~ tienes que hablar de frente cuando hables con otros ~"}, {"tipo": "VOICE_PLAY", "voz1": "voi_favor_s042_ore_0012", "voz2": ""}, {"tipo": "CHAR_TALK", "nombre": "Fuuma", "texto": "\u00a1Por el amor de Dios, est\u00e1 bien!\u00a0\u00a1Te queda bien y te ves linda!\u00a0\u00a1Esas burbujas te hacen lucir a\u00fan m\u00e1s linda!"}, {"tipo": "CHAR_TALK", "nombre": "", "texto": "Sab\u00eda que se burlar\u00eda m\u00e1s de m\u00ed si continuaba resistiendome, as\u00ed que me rend\u00ed y lo grit\u00e9 en voz alta."}, {"tipo": "CHAR_TALK", "nombre": "", "texto": "Las personas cercanas parec\u00edan decir \"Disfr\u00fatalo mientras puedas ~\", pero trate de ignorarlo tanto como puede."}, {"tipo": "VOICE_PLAY", "voz1": "voi_favor_s042_supika_0014", "voz2": ""}, {"tipo": "CHAR_TALK", "nombre": "Spica", "texto": "Heehee ~ \u266a Es lindo y me queda bien ey ~ \u266a Gracias por los cumplidos, Capit\u00e1n \u266a"}, {"tipo": "CHAR_TALK", "nombre": "", "texto": "Spica gir\u00f3 una vez m\u00e1s, satisfecha con mi reacci\u00f3n."}, {"tipo": "CHAR_TALK", "nombre": "", "texto": "Ver a Spica incluso m\u00e1s encantada me di\u00f3 un poco de verg\u00fcenza, pero no me sent\u00ed mal."}, {"tipo": "VOICE_PLAY", "voz1": "voi_favor_s042_ore_0013", "voz2": ""}, {"tipo": "CHAR_TALK", "nombre": "Fuuma", "texto": "Bueno, era un festival despu\u00e9s de todo, \u2026\u2026."}, {"tipo": "CHAR_TALK", "nombre": "", "texto": "Es importante dejarse llevar y divertirse despu\u00e9s de las misiones."}, {"tipo": "VOICE_PLAY", "voz1": "voi_favor_s042_ore_0014", "voz2": ""}, {"tipo": "CHAR_TALK", "nombre": "Fuuma", "texto": "Veamos, para disfrutar de un festival japon\u00e9s, no podemos dejar de lado el algod\u00f3n de az\u00facar y las manzanas dulces, \u00bfverdad?\u00a0\u00bfO a Spica le gustar\u00eda m\u00e1s la galer\u00eda de tiro?"}, {"tipo": "VOICE_PLAY", "voz1": "voi_favor_s042_supika_0015", "voz2": ""}, {"tipo": "CHAR_TALK", "nombre": "Spica", "texto": "Hmm ~ Quiero beber un poco de cerveza primero \u266a La cerveza japonesa es muy fr\u00eda y refrescante ~ \u266a"}, {"tipo": "VOICE_PLAY", "voz1": "voi_favor_s042_ore_0015", "voz2": ""}, {"tipo": "CHAR_TALK", "nombre": "Fuuma", "texto": "Te gusta mucho beber, \u00bfno? ... Normalmente te dir\u00eda que te abstengas, pero es un festival, as\u00ed que..."}, {"tipo": "VOICE_PLAY", "voz1": "voi_favor_s042_supika_0016", "voz2": ""}, {"tipo": "CHAR_TALK", "nombre": "Spica", "texto": "S\u00ed, s\u00ed, porque es un festival, es un festival ~"}, {"tipo": "CHAR_TALK", "nombre": "", "texto": "Una vez m\u00e1s, las burbujas flotaron alrededor y detr\u00e1s de ella mientras saltaba emocionada."}, {"tipo": "CHAR_TALK", "nombre": "", "texto": "Hipnotizados por la fant\u00e1stica vista del festival, Spica\u00a0y yo\u00a0pasamos el mejor momento all\u00ed."}, {"tipo": "TALK_OUT"}, {"tipo": "CLOSE"}], "hime_nc007a": "images/webp/texture/hime_nc007a.webp", "snd_bgm_e_story_002": "audio/ogg/snd_bgm_e_story_002.ogg", "voi_favor_s042_ore_0000": "audio/ogg/voi_favor_s042_ore_0000.ogg", "supporter_042_0": "images/webp/sprite/supporter_042_0.webp", "voi_favor_s042_supika_0000": "audio/ogg/voi_favor_s042_supika_0000.ogg", "voi_favor_s042_supika_0001": "audio/ogg/voi_favor_s042_supika_0001.ogg", "voi_favor_s042_ore_0001": "audio/ogg/voi_favor_s042_ore_0001.ogg", "voi_favor_s042_supika_0002": "audio/ogg/voi_favor_s042_supika_0002.ogg", "voi_favor_s042_ore_0002": "audio/ogg/voi_favor_s042_ore_0002.ogg", "voi_favor_s042_supika_0003": "audio/ogg/voi_favor_s042_supika_0003.ogg", "voi_favor_s042_ore_0003": "audio/ogg/voi_favor_s042_ore_0003.ogg", "voi_favor_s042_supika_0004": "audio/ogg/voi_favor_s042_supika_0004.ogg", "snd_story_run01": "audio/ogg/snd_story_run01.ogg", "voi_favor_s042_ore_0004": "audio/ogg/voi_favor_s042_ore_0004.ogg", "voi_favor_s042_ore_0005": "audio/ogg/voi_favor_s042_ore_0005.ogg", "voi_favor_s042_supika_0005": "audio/ogg/voi_favor_s042_supika_0005.ogg", "voi_favor_s042_ore_0006": "audio/ogg/voi_favor_s042_ore_0006.ogg", "voi_favor_s042_supika_0006": "audio/ogg/voi_favor_s042_supika_0006.ogg", "voi_favor_s042_supika_0007": "audio/ogg/voi_favor_s042_supika_0007.ogg", "voi_favor_s042_ore_0007": "audio/ogg/voi_favor_s042_ore_0007.ogg", "voi_favor_s042_supika_0008": "audio/ogg/voi_favor_s042_supika_0008.ogg", "voi_favor_s042_ore_0008": "audio/ogg/voi_favor_s042_ore_0008.ogg", "voi_favor_s042_supika_0009": "audio/ogg/voi_favor_s042_supika_0009.ogg", "voi_favor_s042_ore_0009": "audio/ogg/voi_favor_s042_ore_0009.ogg", "voi_favor_s042_supika_0010": "audio/ogg/voi_favor_s042_supika_0010.ogg", "voi_favor_s042_ore_0010": "audio/ogg/voi_favor_s042_ore_0010.ogg", "voi_favor_s042_supika_0011": "audio/ogg/voi_favor_s042_supika_0011.ogg", "voi_favor_s042_ore_0011": "audio/ogg/voi_favor_s042_ore_0011.ogg", "voi_favor_s042_supika_0012": "audio/ogg/voi_favor_s042_supika_0012.ogg", "voi_favor_s042_supika_0013": "audio/ogg/voi_favor_s042_supika_0013.ogg", "voi_favor_s042_ore_0012": "audio/ogg/voi_favor_s042_ore_0012.ogg", "voi_favor_s042_supika_0014": "audio/ogg/voi_favor_s042_supika_0014.ogg", "voi_favor_s042_ore_0013": "audio/ogg/voi_favor_s042_ore_0013.ogg", "voi_favor_s042_ore_0014": "audio/ogg/voi_favor_s042_ore_0014.ogg", "voi_favor_s042_supika_0015": "audio/ogg/voi_favor_s042_supika_0015.ogg", "voi_favor_s042_ore_0015": "audio/ogg/voi_favor_s042_ore_0015.ogg", "voi_favor_s042_supika_0016": "audio/ogg/voi_favor_s042_supika_0016.ogg"}