{"script_txt": [{"tipo": "SHOW"}, {"tipo": "TALK_IN"}, {"tipo": "BG_LOAD", "clase": "FADE_IN", "nombre": "bg_black", "time": 2.0, "x_scal": 1.25, "y_scal": 0.938}, {"tipo": "CHAR_TALK", "nombre": "", "texto": "Despu\u00e9s de la escuela, una compa\u00f1era de clase me llam\u00f3 y estaba en la enfermer\u00eda."}, {"tipo": "CHAR_TALK", "nombre": "", "texto": "Esto puede sonar como la fantas\u00eda de cierto adolescente, pero no era nada de eso."}, {"tipo": "BG_LOAD", "clase": "MOVE", "nombre": "supporter_058_0", "time": 2.0, "x_scal": 1.0, "y_scal": 1.0, "efecto": "LEFT_RIGHT"}, {"tipo": "BGM_PLAY", "volumen": 0.5, "nombre": "snd_bgm_e_story_002", "extension": ".ogg"}, {"tipo": "VOICE_PLAY", "voz1": "voi_favor_s058_ore_0000", "voz2": ""}, {"tipo": "CHAR_TALK", "nombre": "Fuuma", "texto": "Oye, espera un segundo, no toques all\u00ed ---"}, {"tipo": "VOICE_PLAY", "voz1": "voi_favor_s058_nanami_0000", "voz2": ""}, {"tipo": "CHAR_TALK", "nombre": "Nanami", "texto": "\u00a1Ah, oye!\u00a0\u00a1No te muevas! \u00a1Todo va muy bien!"}, {"tipo": "CHAR_TALK", "nombre": "", "texto": "La chica agachada frente a m\u00ed era Shinonome Nanami."}, {"tipo": "CHAR_TALK", "nombre": "", "texto": "Una compa\u00f1era de clase de Taimanin, usa arte ninja que cura las heridas a cambio de su resistencia."}, {"tipo": "CHAR_TALK", "nombre": "", "texto": "Pero si intenta curarlo todo con su arte ninja, se agotar\u00e1 r\u00e1pidamente, por lo que quer\u00eda ayuda, ya que tambi\u00e9n quer\u00eda aprender a tratar a las personas normalmente."}, {"tipo": "VOICE_PLAY", "voz1": "voi_favor_s058_nanami_0001", "voz2": ""}, {"tipo": "CHAR_TALK", "nombre": "Nanami", "texto": "\u00a1Nooo!\u00a0\u00a1Lo arruin\u00e9! Est\u00e1 bien, desenvu\u00e9lvelo un poco ... \u00bfEh?\u00a0El vendaje se enred\u00f3."}, {"tipo": "CHAR_TALK", "nombre": "", "texto": "No puedo decir que eso iba realmente bien."}, {"tipo": "VOICE_PLAY", "voz1": "voi_favor_s058_nanami_0002", "voz2": ""}, {"tipo": "CHAR_TALK", "nombre": "Nanami", "texto": "Incline la extremidad de esta manera, envuelva el vendaje no demasiado suelto ni demasiado apretado como \u2026"}, {"tipo": "SE_PLAY", "volumen": 1.0, "nombre": "snd_story_footstep01", "loop": "SE", "extension": ".wav"}, {"tipo": "VOICE_PLAY", "voz1": "voi_favor_s058_ore_0001", "voz2": ""}, {"tipo": "CHAR_TALK", "nombre": "Fuuma", "texto": "\u00bf\u00a1Auch, auch, auch !?\u00a0\u00bf\u00a1Llamas a esto no demasiado apretado !?\u00a0\u00a1El vendaje b\u00e1sicamente se est\u00e1 clavando en mi piel!"}, {"tipo": "VOICE_PLAY", "voz1": "voi_favor_s058_nanami_0003", "voz2": ""}, {"tipo": "CHAR_TALK", "nombre": "Nanami", "texto": "Hmm ~?\u00a0\u00bfHmm?\u00a0\u00bfQu\u00e9 raro ~?\u00a0\u00bfEstoy haciendo exactamente lo que dicen las instrucciones?"}, {"tipo": "CHAR_TALK", "nombre": "", "texto": "Nanami inclin\u00f3 la cabeza confundida, con una expresi\u00f3n facial que dec\u00eda \"\u00bfQu\u00e9 hice mal?\"."}, {"tipo": "CHAR_TALK", "nombre": "", "texto": "Las vendas de mi cuerpo est\u00e1n envueltas demasiado sueltas y demasiado apretadas, ni siquiera envueltas y enredadas, o envueltas\u00a0muy\u00a0firmemente."}, {"tipo": "VOICE_PLAY", "voz1": "voi_favor_s058_ore_0002", "voz2": ""}, {"tipo": "CHAR_TALK", "nombre": "Fuuma", "texto": "\u00bfEst\u00e1s tratando de aprender a envolver una momia?\u00a0\u00bfO dise\u00f1ar un nuevo tipo de vestido para lucirlo en un desfile de moda?"}, {"tipo": "CHAR_TALK", "nombre": "", "texto": "Solo quize preguntarle eso porque ella distra\u00edda, iba de aqu\u00ed para all\u00e1."}, {"tipo": "VOICE_PLAY", "voz1": "voi_favor_s058_nanami_0004", "voz2": ""}, {"tipo": "CHAR_TALK", "nombre": "Nanami", "texto": "\u00a1\u00a1Funcion\u00f3 cuando lo practiqu\u00e9 !! \u00a1Tus extremidades son el problema!"}, {"tipo": "VOICE_PLAY", "voz1": "voi_favor_s058_ore_0003", "voz2": ""}, {"tipo": "CHAR_TALK", "nombre": "Fuuma", "texto": "Oye, no me culpes por tus malas t\u00e9cnicas.\u00a0Mi cuerpo es absolutamente normal."}, {"tipo": "CHAR_TALK", "nombre": "", "texto": "Nanami me mir\u00f3 como si dijera \"Estoy haciendo lo mejor que puedo\", pero no olvid\u00e9 el hecho de que dijo que mi cuerpo ten\u00eda la culpa."}, {"tipo": "VOICE_PLAY", "voz1": "voi_favor_s058_ore_0004", "voz2": ""}, {"tipo": "CHAR_TALK", "nombre": "Fuuma", "texto": "De todos modos, \u00bfQui\u00e9n diablos te ense\u00f1\u00f3 en primer lugar ? Yo tampoco soy tan conocedor, pero parece que desde el principio estabas mal."}, {"tipo": "VOICE_PLAY", "voz1": "voi_favor_s058_nanami_0005", "voz2": ""}, {"tipo": "CHAR_TALK", "nombre": "Nanami", "texto": "??\u00a0Ahora que lo mencionas, aparte de la clase, Mari-chan, Mai-chan \u2026\u2026.\u00a0Oh, y la se\u00f1orita Saika me est\u00e1n ayudando con esto."}, {"tipo": "VOICE_PLAY", "voz1": "voi_favor_s058_ore_0005", "voz2": ""}, {"tipo": "CHAR_TALK", "nombre": "Fuuma", "texto": "Ellas son buenas en estas cosas, por lo que no son ellas quienes te ense\u00f1aron incorrectamente.\u00a0Quiz\u00e1s eres solo t\u00fa quien apesta en esto."}, {"tipo": "VOICE_PLAY", "voz1": "voi_favor_s058_nanami_0006", "voz2": ""}, {"tipo": "CHAR_TALK", "nombre": "Nanami", "texto": "\u00bf\u00a1Qu\u00e9!?\u00a0Eso es demasiado cruel, \u00bfno crees? Quiero decir, s\u00e9 que apesto, pero es exactamente por eso que estoy tratando de practicar, \u00bfno?"}, {"tipo": "CHAR_TALK", "nombre": "", "texto": "S\u00e9 que no le gust\u00f3 lo que dije, pero tambi\u00e9n sabe que no es tan buena en esto."}, {"tipo": "CHAR_TALK", "nombre": "", "texto": "Estaba envolviendo el vendaje como si supiera lo que estaba haciendo, pero no iba a ninguna parte."}, {"tipo": "SE_PLAY", "volumen": 1.0, "nombre": "snd_story_footstep01", "loop": "SE", "extension": ".wav"}, {"tipo": "VOICE_PLAY", "voz1": "voi_favor_s058_ore_0006", "voz2": ""}, {"tipo": "CHAR_TALK", "nombre": "Fuuma", "texto": "\u00a1Hey hey hey!\u00a0Al diablo las instrucciones, \u00a1no est\u00e1 poniendo ning\u00fan esfuerzo en ello!\u00a0Todas tus t\u00e9cnicas, y cu\u00e1nta fuerza aplicas es ...... \u00a1ME DUELE !"}, {"tipo": "VOICE_PLAY", "voz1": "voi_favor_s058_nanami_0007", "voz2": ""}, {"tipo": "CHAR_TALK", "nombre": "Nanami", "texto": "\u00a1Ya c\u00e1llate!\u00a0Estoy tratando de concentrarme pero sigues ladrando en mi o\u00eddo, \u00a1as\u00ed que se me est\u00e1 olvidando todo lo que aprend\u00ed!"}, {"tipo": "SE_PLAY", "volumen": 1.0, "nombre": "snd_story_footstep01", "loop": "SE", "extension": ".wav"}, {"tipo": "CHAR_TALK", "nombre": "", "texto": "Me call\u00f3 apretando el vendaje y continu\u00f3."}, {"tipo": "VOICE_PLAY", "voz1": "voi_favor_s058_nanami_0008", "voz2": ""}, {"tipo": "CHAR_TALK", "nombre": "Nanami", "texto": "Cuando lo aprend\u00ed por primera vez, definitivamente fue as\u00ed primero, luego as\u00ed\u2026 \u00a1Mhmm!\u00a0\u00bfera esta la manera correcta?"}, {"tipo": "CHAR_TALK", "nombre": "", "texto": "Pod\u00eda verla tratando de recordar lo que hab\u00eda aprendido, porque estaba entrecerrando los ojos y esforz\u00e1ndose mucho, pero el orden de las instrucciones y la fuerza se confund\u00edan en su cabeza."}, {"tipo": "VOICE_PLAY", "voz1": "voi_favor_s058_nanami_0009", "voz2": ""}, {"tipo": "CHAR_TALK", "nombre": "Nanami", "texto": "\u00a1Ugh-!\u00a0Fall\u00e9 de nuevo ...... \u00a1Pero creo ahora s\u00ed ya lo he dominado!"}, {"tipo": "CHAR_TALK", "nombre": "", "texto": "Probablemente no tenga ni idea de lo que ha hecho mal, pero no se detiene."}, {"tipo": "CHAR_TALK", "nombre": "", "texto": "S\u00e9 que no tiene malas intenciones y que s\u00f3lo hace todo lo posible para ayudar a los dem\u00e1s."}, {"tipo": "CHAR_TALK", "nombre": "", "texto": "Es s\u00f3lo que, \u00bfpor qu\u00e9 tengo que ser yo quien est\u00e9 pasando por este sufrimiento?"}, {"tipo": "VOICE_PLAY", "voz1": "voi_favor_s058_nanami_0010", "voz2": ""}, {"tipo": "CHAR_TALK", "nombre": "Nanami", "texto": "\u00a1Bueno!\u00a0\u00a1Una vez m\u00e1s!\u00a0\u00a1Esta vez 'c\u00f3mo envolver heridas en los abdominales'! ......"}, {"tipo": "SE_PLAY", "volumen": 1.0, "nombre": "snd_story_footstep01", "loop": "SE", "extension": ".wav"}, {"tipo": "VOICE_PLAY", "voz1": "voi_favor_s058_ore_0007", "voz2": ""}, {"tipo": "CHAR_TALK", "nombre": "Fuuma", "texto": "\u00a1So... s\u00f3lo un poco m\u00e1s de cuidado \u2026\u2026.! Auch, mi pecho, mi pecho, est\u00e1 demasiado apretado \u2026\u2026 !?"}, {"tipo": "VOICE_PLAY", "voz1": "voi_favor_s058_nanami_0011", "voz2": ""}, {"tipo": "CHAR_TALK", "nombre": "Nanami", "texto": "Ah ~, \u00bfpuedo presionarlo m\u00e1s?\u00a0La se\u00f1orita Saika dijo que pusiera tanta presi\u00f3n como pudiera para detener la sangre."}, {"tipo": "SE_PLAY", "volumen": 1.0, "nombre": "snd_story_footstep01", "loop": "SE", "extension": ".wav"}, {"tipo": "VOICE_PLAY", "voz1": "voi_favor_s058_ore_0008", "voz2": ""}, {"tipo": "CHAR_TALK", "nombre": "Fuuma", "texto": "\u00bf\u00a1Auchh \u2026\u2026 !?\u00a0\u00a1Espe.. demasiado apretado! ....... \u00a1Ahhggggg ......!"}, {"tipo": "CHAR_TALK", "nombre": "", "texto": "Nanami puso las vendas demasiado apretadas y me imped\u00edan respirar."}, {"tipo": "CHAR_TALK", "nombre": "", "texto": "Intent\u00e9 decirle que se detuviera, pero solo logr\u00e9 jadear."}, {"tipo": "VOICE_PLAY", "voz1": "voi_favor_s058_nanami_0012", "voz2": ""}, {"tipo": "CHAR_TALK", "nombre": "Nanami", "texto": "Hmm ~, se ve un poco mal, \u00a1pero creo que presion\u00e9 mucho la herida!\u00a0\u00a1Practiquemos en tu cabeza ahora!"}, {"tipo": "SE_PLAY", "volumen": 1.0, "nombre": "snd_story_footstep01", "loop": "SE", "extension": ".wav"}, {"tipo": "VOICE_PLAY", "voz1": "voi_favor_s058_ore_0009", "voz2": ""}, {"tipo": "CHAR_TALK", "nombre": "Fuuma", "texto": "\u00bf\u00a1Cbz !?\u00a0\u00a1\u00a1O \u2026\u2026\u2026 k ~ !!"}, {"tipo": "VOICE_PLAY", "voz1": "voi_favor_s058_nanami_0013", "voz2": ""}, {"tipo": "CHAR_TALK", "nombre": "Nanami", "texto": "\u00a1Uf, oye!\u00a0\u00a1No puedo envolverla correctamente si sigues movi\u00e9ndote! Mari-chan me dijo que primero envuelva la sien, luego alrededor de las partes que no est\u00e1n heridas, ya que la cabeza sangra f\u00e1cilmente ..."}, {"tipo": "SE_PLAY", "volumen": 1.0, "nombre": "snd_story_footstep01", "loop": "SE", "extension": ".wav"}, {"tipo": "VOICE_PLAY", "voz1": "voi_favor_s058_ore_0010", "voz2": ""}, {"tipo": "CHAR_TALK", "nombre": "Fuuma", "texto": "\u2026\u2026 !!\u00a0\u2026\u2026\u2026\u2026 !!"}, {"tipo": "CHAR_TALK", "nombre": "", "texto": "El vendaje que se supon\u00eda iba a envolver mi cabeza envolvi\u00f3 mis ojos, apret\u00f3 mi nariz y bloque\u00f3 mi boca."}, {"tipo": "CHAR_TALK", "nombre": "", "texto": "Antes por lo menos pod\u00eda respirar con dificultad por la presi\u00f3n del vendaje alrededor de mi pecho, pero ahora ni siquiera pod\u00eda respirar."}, {"tipo": "VOICE_PLAY", "voz1": "voi_favor_s058_nanami_0014", "voz2": ""}, {"tipo": "CHAR_TALK", "nombre": "Nanami", "texto": "S\u00ed ~ ah, s\u00f3lo necesitaba envolverlo a mi manera.\u00a0\u00a1Tambi\u00e9n puedo hacerlo si me concentro!"}, {"tipo": "CHAR_TALK", "nombre": "", "texto": "Nanami estaba demasiado concentrada para notar mi sufrimiento y continu\u00f3 envolvi\u00e9ndome felizmente."}, {"tipo": "BG_LOAD", "clase": "MOVE", "nombre": "bg_black", "time": 2.0, "x_scal": 1.25, "y_scal": 0.938, "efecto": "UP_DOWN"}, {"tipo": "VOICE_PLAY", "voz1": "voi_favor_s058_nanami_0015", "voz2": ""}, {"tipo": "CHAR_TALK", "nombre": "Nanami", "texto": "S\u00ed, \u00a1todo listo!\u00a0\u00a1Perfecto!\u00a0\u00bfQu\u00e9 piensas Fuuma \u2026\u2026 Hmm?"}, {"tipo": "CHAR_TALK", "nombre": "", "texto": "Nanami se limpi\u00f3 el sudor de la frente con un \"Uf\" y volvi\u00f3 a inclinar la cabeza."}, {"tipo": "VOICE_PLAY", "voz1": "voi_favor_s058_ore_0011", "voz2": ""}, {"tipo": "CHAR_TALK", "nombre": "Fuuma", "texto": "\u2026\u2026\u2026\u2026"}, {"tipo": "VOICE_PLAY", "voz1": "voi_favor_s058_nanami_0016", "voz2": ""}, {"tipo": "CHAR_TALK", "nombre": "Nanami", "texto": "Umm \u2026\u2026 \u00bfTe envolv\u00ed demasiado?"}, {"tipo": "VOICE_PLAY", "voz1": "voi_favor_s058_ore_0012", "voz2": ""}, {"tipo": "CHAR_TALK", "nombre": "Fuuma", "texto": "\u2026\u2026\u2026\u2026"}, {"tipo": "CHAR_TALK", "nombre": "", "texto": "Asenti.\u00a0Gracias a ella me convert\u00ed en una momia."}, {"tipo": "VOICE_PLAY", "voz1": "voi_favor_s058_nanami_0017", "voz2": ""}, {"tipo": "CHAR_TALK", "nombre": "Nanami", "texto": "\u00a1Wo, woaaaah!\u00a0\u00a1Lo siento!\u00a0\u00a1Te desenvolver\u00e9 ahora!\u00a0\u00bfEh?\u00a0Lo envolv\u00ed as\u00ed, por lo que deber\u00eda desenvolverlo as\u00ed ..."}, {"tipo": "CHAR_TALK", "nombre": "", "texto": "Ella entr\u00f3 en p\u00e1nico y comenz\u00f3 a desenvolverme, pero el comienzo fue tan malo, que obviamente, el desenvolver tampoco iba a salir bien."}, {"tipo": "VOICE_PLAY", "voz1": "voi_favor_s058_nanami_0018", "voz2": ""}, {"tipo": "CHAR_TALK", "nombre": "Nanami", "texto": "Oh, \u00bf\u00a1por qu\u00e9 est\u00e1 enredado el vendaje all\u00ed !?\u00a0Fu, Fuuma?\u00a0Tu piel se est\u00e1 poniendo morada, \u00bf\u00a1est\u00e1s seguro de que est\u00e1s bien !?"}, {"tipo": "VOICE_PLAY", "voz1": "voi_favor_s058_ore_0013", "voz2": ""}, {"tipo": "CHAR_TALK", "nombre": "Fuuma", "texto": "(La pr\u00f3xima vez, mejor le digo que traiga a alguien que pueda ense\u00f1arle a envolver correctamente y le diga cu\u00e1ndo parar \u2026\u2026)"}, {"tipo": "CHAR_TALK", "nombre": "", "texto": "Ese fue el \u00faltimo pensamiento en mi mente mientras perd\u00eda lentamente la conciencia."}, {"tipo": "TALK_OUT"}, {"tipo": "CLOSE"}], "bg_black": "images/webp/texture/bg_black.webp", "supporter_058_0": "images/webp/sprite/supporter_058_0.webp", "snd_bgm_e_story_002": "audio/ogg/snd_bgm_e_story_002.ogg", "voi_favor_s058_ore_0000": "audio/ogg/voi_favor_s058_ore_0000.ogg", "voi_favor_s058_nanami_0000": "audio/ogg/voi_favor_s058_nanami_0000.ogg", "voi_favor_s058_nanami_0001": "audio/ogg/voi_favor_s058_nanami_0001.ogg", "voi_favor_s058_nanami_0002": "audio/ogg/voi_favor_s058_nanami_0002.ogg", "snd_story_footstep01": "audio/wav/snd_story_footstep01.wav", "voi_favor_s058_ore_0001": "audio/ogg/voi_favor_s058_ore_0001.ogg", "voi_favor_s058_nanami_0003": "audio/ogg/voi_favor_s058_nanami_0003.ogg", "voi_favor_s058_ore_0002": "audio/ogg/voi_favor_s058_ore_0002.ogg", "voi_favor_s058_nanami_0004": "audio/ogg/voi_favor_s058_nanami_0004.ogg", "voi_favor_s058_ore_0003": "audio/ogg/voi_favor_s058_ore_0003.ogg", "voi_favor_s058_ore_0004": "audio/ogg/voi_favor_s058_ore_0004.ogg", "voi_favor_s058_nanami_0005": "audio/ogg/voi_favor_s058_nanami_0005.ogg", "voi_favor_s058_ore_0005": "audio/ogg/voi_favor_s058_ore_0005.ogg", "voi_favor_s058_nanami_0006": "audio/ogg/voi_favor_s058_nanami_0006.ogg", "voi_favor_s058_ore_0006": "audio/ogg/voi_favor_s058_ore_0006.ogg", "voi_favor_s058_nanami_0007": "audio/ogg/voi_favor_s058_nanami_0007.ogg", "voi_favor_s058_nanami_0008": "audio/ogg/voi_favor_s058_nanami_0008.ogg", "voi_favor_s058_nanami_0009": "audio/ogg/voi_favor_s058_nanami_0009.ogg", "voi_favor_s058_nanami_0010": "audio/ogg/voi_favor_s058_nanami_0010.ogg", "voi_favor_s058_ore_0007": "audio/ogg/voi_favor_s058_ore_0007.ogg", "voi_favor_s058_nanami_0011": "audio/ogg/voi_favor_s058_nanami_0011.ogg", "voi_favor_s058_ore_0008": "audio/ogg/voi_favor_s058_ore_0008.ogg", "voi_favor_s058_nanami_0012": "audio/ogg/voi_favor_s058_nanami_0012.ogg", "voi_favor_s058_ore_0009": "audio/ogg/voi_favor_s058_ore_0009.ogg", "voi_favor_s058_nanami_0013": "audio/ogg/voi_favor_s058_nanami_0013.ogg", "voi_favor_s058_ore_0010": "audio/ogg/voi_favor_s058_ore_0010.ogg", "voi_favor_s058_nanami_0014": "audio/ogg/voi_favor_s058_nanami_0014.ogg", "voi_favor_s058_nanami_0015": "audio/ogg/voi_favor_s058_nanami_0015.ogg", "voi_favor_s058_ore_0011": "audio/ogg/voi_favor_s058_ore_0011.ogg", "voi_favor_s058_nanami_0016": "audio/ogg/voi_favor_s058_nanami_0016.ogg", "voi_favor_s058_ore_0012": "audio/ogg/voi_favor_s058_ore_0012.ogg", "voi_favor_s058_nanami_0017": "audio/ogg/voi_favor_s058_nanami_0017.ogg", "voi_favor_s058_nanami_0018": "audio/ogg/voi_favor_s058_nanami_0018.ogg", "voi_favor_s058_ore_0013": "audio/ogg/voi_favor_s058_ore_0013.ogg"}