{"script_txt": [{"tipo": "SHOW"}, {"tipo": "TALK_IN"}, {"tipo": "BG_LOAD", "clase": "FADE_IN", "nombre": "bg_black", "time": 2.0, "x_scal": 1.25, "y_scal": 0.938}, {"tipo": "BGM_PLAY", "volumen": 0.5, "nombre": "snd_bgm_story_004", "extension": ".ogg"}, {"tipo": "VOICE_PLAY", "voz1": "voi_favor_c011_asuka_0000", "voz2": ""}, {"tipo": "CHAR_TALK", "nombre": "Asuka", "texto": "Yo me ocupar\u00e9 de este lugar, \u00a1as\u00ed que v\u00e1yanse!"}, {"tipo": "VOICE_PLAY", "voz1": "voi_favor_c011_ore_0000", "voz2": ""}, {"tipo": "CHAR_TALK", "nombre": "Fuuma", "texto": "\u00a1No, no te dejar\u00e9!"}, {"tipo": "VOICE_PLAY", "voz1": "voi_favor_c011_asuka_0001", "voz2": ""}, {"tipo": "CHAR_TALK", "nombre": "Asuka", "texto": "\u00a1De qu\u00e9 est\u00e1s hablando! \u00a1Eres responsable de proteger las fuerzas!"}, {"tipo": "VOICE_PLAY", "voz1": "voi_favor_c011_ore_0001", "voz2": ""}, {"tipo": "CHAR_TALK", "nombre": "Fuuma", "texto": "Pero... Dudo que puedas enfrentarte a tantos por tu cuenta..."}, {"tipo": "VOICE_PLAY", "voz1": "voi_favor_c011_asuka_0002", "voz2": ""}, {"tipo": "CHAR_TALK", "nombre": "Asuka", "texto": "Parece que me subestimaste. Infiltrarme sola en este lugar, era mi plan principal. S\u00f3lo result\u00f3 que est\u00e1bamos en el mismo caso sobre Momochi Toyo."}, {"tipo": "VOICE_PLAY", "voz1": "voi_favor_c011_asuka_0003", "voz2": ""}, {"tipo": "CHAR_TALK", "nombre": "Asuka", "texto": "La raz\u00f3n por la que luch\u00e9 contigo fue porque eras t\u00fa quien lideraba las Fuerzas Especiales. Si no fuera as\u00ed, no me hubiera involucrado mientras no estuvieran en mi camino."}, {"tipo": "VOICE_PLAY", "voz1": "voi_favor_c011_asuka_0004", "voz2": ""}, {"tipo": "CHAR_TALK", "nombre": "Asuka", "texto": "No soy como ustedes, que tienen que trabajar excesivamente para luchar, \u00bfde acuerdo? \u00a1Ahora salgan de aqu\u00ed!"}, {"tipo": "VOICE_PLAY", "voz1": "voi_favor_c011_ore_0002", "voz2": ""}, {"tipo": "CHAR_TALK", "nombre": "Fuuma", "texto": "\u2026\u2026Bien. Nos vemos luego. Te lo agradecer\u00e9 m\u00e1s tarde cuando regreses, as\u00ed que ten cuidado."}, {"tipo": "VOICE_PLAY", "voz1": "voi_favor_c011_asuka_0005", "voz2": ""}, {"tipo": "CHAR_TALK", "nombre": "Asuka", "texto": "Mira quien habla. Soy Koukawa Asuka... La Parca de Acero."}, {"tipo": "BGM_STOP", "fadeout": "none"}, {"tipo": "CHAR_TALK", "nombre": "", "texto": "\u2026\u2026\u2026\u2026"}, {"tipo": "BG_LOAD", "clase": "MOVE", "nombre": "char_11_0", "time": 2.0, "x_scal": 1.0, "y_scal": 1.0, "efecto": "LEFT_RIGHT"}, {"tipo": "BG_LOAD", "clase": "ADD", "nombre": "char_11_b", "time": 0.0, "offset_x": "377", "offset_y": "197", "in_out": "IN"}, {"tipo": "VOICE_PLAY", "voz1": "voi_favor_c011_asuka_0006", "voz2": ""}, {"tipo": "CHAR_TALK", "nombre": "Asuka", "texto": "\u2026\u2026 \u00a1Kahaak! Ja, ja"}, {"tipo": "BGM_PLAY", "volumen": 0.5, "nombre": "snd_bgm_story_003", "extension": ".ogg"}, {"tipo": "CHAR_TALK", "nombre": "", "texto": "Un sue\u00f1o breve\u2026 Asuka estaba recordando una breve conversaci\u00f3n de diez minutos y luego se despert\u00f3."}, {"tipo": "CHAR_TALK", "nombre": "", "texto": "Se levant\u00f3, pensando \"Solo estuve inconsciente por unos segundos, pero si esto hubiera sucedido durante el combate, habr\u00eda muerto\"."}, {"tipo": "CHAR_TALK", "nombre": "", "texto": "Pero todo lo que la rodeaba eran cuerpos de sus enemigos y pilares y muros a punto de derrumbarse."}, {"tipo": "CHAR_TALK", "nombre": "", "texto": "Se apoy\u00f3 en una pared, record\u00e1ndose a s\u00ed misma haciendo toda esa destrucci\u00f3n."}, {"tipo": "BG_LOAD", "clase": "ADD", "nombre": "char_11_b", "time": 0.2, "offset_x": "377", "offset_y": "197", "in_out": "OUT"}, {"tipo": "VOICE_PLAY", "voz1": "voi_favor_c011_asuka_0007", "voz2": ""}, {"tipo": "CHAR_TALK", "nombre": "Asuka", "texto": "Owowowow\u2026 Wow, est\u00e1 absolutamente destruido. Tal vez me la llev\u00e9 muy leve por demasiado tiempo."}, {"tipo": "CHAR_TALK", "nombre": "", "texto": "Asuka refunfu\u00f1\u00f3 en la instalaci\u00f3n que ya comenzaba a colapsar."}, {"tipo": "CHAR_TALK", "nombre": "", "texto": "No se estaba tomando su tiempo, pero no es que no comprendiese lo terrible que era la situaci\u00f3n en ese momento."}, {"tipo": "CHAR_TALK", "nombre": "", "texto": "Sus dos extremidades androides estaban demasiado da\u00f1adas, lo que le imped\u00eda moverse."}, {"tipo": "CHAR_TALK", "nombre": "", "texto": "La batalla fue as\u00ed de dura."}, {"tipo": "BG_LOAD", "clase": "ADD", "nombre": "char_11_a", "time": 0.0, "offset_x": "377", "offset_y": "197", "in_out": "IN"}, {"tipo": "VOICE_PLAY", "voz1": "voi_favor_c011_asuka_0008", "voz2": ""}, {"tipo": "CHAR_TALK", "nombre": "Asuka", "texto": "\u00bfCalcul\u00e9 mal la fuerza del enemigo? \u00bfMe dej\u00e9 llevar\u2026?"}, {"tipo": "CHAR_TALK", "nombre": "", "texto": "Asuka murmur\u00f3. Pero no fue eso."}, {"tipo": "CHAR_TALK", "nombre": "", "texto": "Al principio, s\u00f3lo las fuerzas militares de Nomad estaban ah\u00ed."}, {"tipo": "CHAR_TALK", "nombre": "", "texto": "Pero ella y las Fuerzas Especiales tuvieron la mala suerte de encontrarse tambi\u00e9n con las fuerzas de Astaroth."}, {"tipo": "CHAR_TALK", "nombre": "", "texto": "Pero Asuka no lo sab\u00eda, no hab\u00eda forma de que ella lo supiera."}, {"tipo": "BG_LOAD", "clase": "ADD", "nombre": "char_11_a", "time": 0.2, "offset_x": "377", "offset_y": "197", "in_out": "OUT"}, {"tipo": "VOICE_PLAY", "voz1": "voi_favor_c011_asuka_0009", "voz2": ""}, {"tipo": "CHAR_TALK", "nombre": "Asuka", "texto": "No tiene sentido pensar las cosas\u2026 Tengo que encontrar una manera de salir de aqu\u00ed. Todav\u00eda necesito que Fuuma me agradezca ... \u00a1Oot!"}, {"tipo": "CHAR_TALK", "nombre": "", "texto": "Pero Asuka no se rindi\u00f3, ni un poco."}, {"tipo": "CHAR_TALK", "nombre": "", "texto": "Asuka estaba decidida a escapar, incluso sin ambos brazos y piernas. Estaba decidida a gatear o aferrarse a algo solo con los dientes. As\u00ed que, comenz\u00f3 a mecer su cuerpo."}, {"tipo": "CHAR_TALK", "nombre": "", "texto": "Pero la realidad duele. Incluso si no te rindes, no importa cu\u00e1n determinado est\u00e9s, algunas veces no puedes hacer nada al respecto."}, {"tipo": "CHAR_TALK", "nombre": "", "texto": "Intent\u00f3 algunas cosas, pero no funcionaron. De inmediato pens\u00f3 en otras formas, pero..."}, {"tipo": "BGM_STOP", "fadeout": "none"}, {"tipo": "SE_PLAY", "volumen": 1.0, "nombre": "snd_story_explosion01", "loop": "SE", "extension": ".ogg"}, {"tipo": "TALK", "time": 1.0}, {"tipo": "BG_LOAD", "clase": "ADD", "nombre": "char_11_b", "time": 0.2, "offset_x": "377", "offset_y": "197", "in_out": "IN"}, {"tipo": "VOICE_PLAY", "voz1": "voi_favor_c011_asuka_0010", "voz2": ""}, {"tipo": "CHAR_TALK", "nombre": "Asuka", "texto": "\u00a1\u00a1\u00a1\u00a1\u2026\u2026\u2026!! Eh, ahh. Ahhh\u2026\u2026"}, {"tipo": "CHAR_TALK", "nombre": "", "texto": "Con un gran sonido de colapso, un pilar cay\u00f3 y bloque\u00f3 la entrada."}, {"tipo": "CHAR_TALK", "nombre": "", "texto": "Ahora, incluso si llegaba a la entrada, no hab\u00eda forma de que saliese."}, {"tipo": "BGM_PLAY", "volumen": 0.5, "nombre": "snd_bgm_e_story_003", "extension": ".ogg"}, {"tipo": "BG_LOAD", "clase": "ADD", "nombre": "char_11_b", "time": 0.0, "offset_x": "377", "offset_y": "197", "in_out": "OUT"}, {"tipo": "BG_LOAD", "clase": "ADD", "nombre": "char_11_a", "time": 0.0, "offset_x": "377", "offset_y": "197", "in_out": "IN"}, {"tipo": "VOICE_PLAY", "voz1": "voi_favor_c011_asuka_0011", "voz2": ""}, {"tipo": "CHAR_TALK", "nombre": "Asuka", "texto": "Hah... Sab\u00eda que este d\u00eda llegar\u00eda, alg\u00fan d\u00eda, pero."}, {"tipo": "CHAR_TALK", "nombre": "", "texto": "Asuka murmur\u00f3 impotente. Lo que sinti\u00f3 en su coraz\u00f3n en ese momento\u2026 fue gratitud."}, {"tipo": "CHAR_TALK", "nombre": "", "texto": "Cuando su familia fue masacrada, cuando perdi\u00f3 todas sus extremidades, deber\u00eda haber muerto en ambas ocasiones."}, {"tipo": "CHAR_TALK", "nombre": "", "texto": "Asuka sinti\u00f3 que la raz\u00f3n por la que pudo vivir tanto tiempo fue gracias a todos los que la rodeaban."}, {"tipo": "CHAR_TALK", "nombre": "", "texto": "Taimanin enmascarados, Asagi, Sakura, Murasaki, Kurenai. Mientras dec\u00eda todos sus nombres les agradec\u00eda a cada uno de ellos."}, {"tipo": "BG_LOAD", "clase": "ADD", "nombre": "char_11_a", "time": 0.0, "offset_x": "377", "offset_y": "197", "in_out": "OUT"}, {"tipo": "VOICE_PLAY", "voz1": "voi_favor_c011_asuka_0012", "voz2": ""}, {"tipo": "CHAR_TALK", "nombre": "Asuka", "texto": "Todos, muchas gracias... Fuuma... Huhu, no t\u00fa, no, te lo dir\u00e9 cuando vuelva como un fantasma..."}, {"tipo": "CHAR_TALK", "nombre": "", "texto": "Asuka se mantuvo firme, pero su voz no."}, {"tipo": "CHAR_TALK", "nombre": "", "texto": "Cerr\u00f3 los ojos como para rezar para que muriese al instante y sin dolor."}, {"tipo": "CHAR_TALK", "nombre": "", "texto": "Ese momento."}, {"tipo": "VOICE_PLAY", "voz1": "voi_favor_c011_ore_0003", "voz2": ""}, {"tipo": "CHAR_TALK", "nombre": "Fuuma", "texto": "Asu\u2500\u2500\u2500\u2500\u2500\u2500\u2500\u2500\u2500\u2500\u2500ka !!!"}, {"tipo": "SE_PLAY", "volumen": 1.0, "nombre": "snd_story_explosion01", "loop": "SE", "extension": ".ogg"}, {"tipo": "ALL", "time": 1.0}, {"tipo": "CHAR_TALK", "nombre": "", "texto": "El pilar estall\u00f3 con una explosi\u00f3n y una voz tan fuerte como el ruido de la explosi\u00f3n, se pudo escuchar."}, {"tipo": "BG_LOAD", "clase": "MOVE", "nombre": "char_11_d", "time": 2.0, "x_scal": 1.0, "y_scal": 1.0, "efecto": "LEFT_RIGHT"}, {"tipo": "VOICE_PLAY", "voz1": "voi_favor_c011_asuka_0013", "voz2": ""}, {"tipo": "CHAR_TALK", "nombre": "Asuka", "texto": "Fu, Fuuma? C\u00f3, c\u00f3mo..."}, {"tipo": "CHAR_TALK", "nombre": "", "texto": "Al mirar a la persona que sus labios acababan de pronunciar, pens\u00f3 que estaba viendo cosas al principio."}, {"tipo": "CHAR_TALK", "nombre": "", "texto": "No hab\u00eda garant\u00eda de que pudiera escapar porque el edificio estaba a punto de colapsar por completo."}, {"tipo": "CHAR_TALK", "nombre": "", "texto": "Y no habr\u00eda ning\u00fan idiota en el mundo que regresara para rescatar a alguien que ni siquiera era su compa\u00f1ero de equipo."}, {"tipo": "VOICE_PLAY", "voz1": "voi_favor_c011_ore_0004", "voz2": ""}, {"tipo": "CHAR_TALK", "nombre": "Fuuma", "texto": "Asuka, \u00bfest\u00e1s bien? Supongo que no\u2026 \u00a1Pero est\u00e1s viva, verdad ?!"}, {"tipo": "CHAR_TALK", "nombre": "", "texto": "Pero cuando esa persona se agach\u00f3 frente a ella, la toc\u00f3, su toque, su temperatura y su olor\u2026 Era Fuuma."}, {"tipo": "VOICE_PLAY", "voz1": "voi_favor_c011_asuka_0014", "voz2": ""}, {"tipo": "CHAR_TALK", "nombre": "Asuka", "texto": "Ufff\u2026 \u00bfPor qu\u00e9 regresaste\u2026 Eres un idiota\u2026 Te ayud\u00e9 a escapar."}, {"tipo": "CHAR_TALK", "nombre": "", "texto": "Asuka murmur\u00f3 estupefacta. Quer\u00eda saludarlo con una broma est\u00fapida como siempre hac\u00eda, pero una maldici\u00f3n sali\u00f3 de su boca."}, {"tipo": "CHAR_TALK", "nombre": "", "texto": "Si no lo hac\u00eda, sent\u00eda que iba a estallar en l\u00e1grimas y llorar."}, {"tipo": "CHAR_TALK", "nombre": "", "texto": "Porque estaba feliz de que \u00e9l regresara por ella, porque no quer\u00eda que la viera as\u00ed..."}, {"tipo": "CHAR_TALK", "nombre": "", "texto": "Sinti\u00f3 que iba a llorar como una ni\u00f1a, lo cual no era t\u00edpico de la Parca de Acero."}, {"tipo": "VOICE_PLAY", "voz1": "voi_favor_c011_ore_0005", "voz2": ""}, {"tipo": "CHAR_TALK", "nombre": "Fuuma", "texto": "Lo siento\u2026\u2026 Lo siento, Asuka."}, {"tipo": "CHAR_TALK", "nombre": "", "texto": "Ya sea que Fuuma haya notado o no sus sentimientos, se disculp\u00f3, mir\u00f3 sus extremidades androides y volvi\u00f3 a disculparse nuevamente."}, {"tipo": "CHAR_TALK", "nombre": "", "texto": "Asuka no quer\u00eda escuchar... No quer\u00eda hablar."}, {"tipo": "CHAR_TALK", "nombre": "", "texto": "Pero esta vez no pudo reaccionar en absoluto."}, {"tipo": "SE_PLAY", "volumen": 1.0, "nombre": "snd_story_explosion03", "loop": "SE", "extension": ".ogg"}, {"tipo": "CHAR_TALK", "nombre": "", "texto": "Antes de que Fuuma se diera cuenta el estado de Asuka, otro pilar cay\u00f3."}, {"tipo": "VOICE_PLAY", "voz1": "voi_favor_c011_asuka_0015", "voz2": ""}, {"tipo": "CHAR_TALK", "nombre": "Asuka", "texto": "\u00a1\u00bfAy ?!"}, {"tipo": "VOICE_PLAY", "voz1": "voi_favor_c011_ore_0006", "voz2": ""}, {"tipo": "CHAR_TALK", "nombre": "Fuuma", "texto": "\u00a1Kukh! No es momento de charlar\u2026 \u00a1Lo siento Asuka!"}, {"tipo": "SE_PLAY", "volumen": 1.0, "nombre": "snd_story_explosion02", "loop": "SE", "extension": ".ogg"}, {"tipo": "ALL", "time": 1.0}, {"tipo": "CHAR_TALK", "nombre": "", "texto": "El techo comienza a retumbar, lo que indica que realmente se les estaba acabando el tiempo."}, {"tipo": "CHAR_TALK", "nombre": "", "texto": "Fuuma se disculp\u00f3 de nuevo, la carg\u00f3 y comenz\u00f3 a correr."}, {"tipo": "SE_PLAY", "volumen": 1.0, "nombre": "snd_story_run01", "loop": "SE", "extension": ".ogg"}, {"tipo": "BG_LOAD", "clase": "MOVE", "nombre": "char_11_c", "time": 2.0, "x_scal": 1.0, "y_scal": 1.0, "efecto": "RIGHT_LEFT"}, {"tipo": "VOICE_PLAY", "voz1": "voi_favor_c011_asuka_0016", "voz2": ""}, {"tipo": "CHAR_TALK", "nombre": "Asuka", "texto": "Uh, e..... espera......"}, {"tipo": "CHAR_TALK", "nombre": "", "texto": "Justo cuando Asuka estaba a punto de llorar, sinti\u00f3 una oleada de emociones cuando Fuuma la sostuvo y comenz\u00f3 a correr."}, {"tipo": "CHAR_TALK", "nombre": "", "texto": "Su ritmo card\u00edaco comenz\u00f3 a aumentar debido a la cercan\u00eda de sus rostros y ella quer\u00eda alejarse de \u00e9l."}, {"tipo": "VOICE_PLAY", "voz1": "voi_favor_c011_ore_0007", "voz2": ""}, {"tipo": "CHAR_TALK", "nombre": "Fuuma", "texto": "Bien, te lo iba a decir m\u00e1s tarde. Pero no sabemos qu\u00e9 pasar\u00e1 despu\u00e9s, as\u00ed que te lo dir\u00e9 ahora."}, {"tipo": "VOICE_PLAY", "voz1": "voi_favor_c011_asuka_0017", "voz2": ""}, {"tipo": "CHAR_TALK", "nombre": "Asuka", "texto": "\u00bf\u2026\u2026\u2026\u2026?"}, {"tipo": "VOICE_PLAY", "voz1": "voi_favor_c011_ore_0008", "voz2": ""}, {"tipo": "CHAR_TALK", "nombre": "Fuuma", "texto": "Gracias, Asuka\u2026\u2026 \u00a1Gracias! \u00a1De verdad!"}, {"tipo": "CHAR_TALK", "nombre": "", "texto": "Fuuma dijo de repente lo que Asuka siempre quiso escuchar de \u00e9l."}, {"tipo": "VOICE_PLAY", "voz1": "voi_favor_c011_asuka_0018", "voz2": ""}, {"tipo": "CHAR_TALK", "nombre": "Asuka", "texto": "\u00bfQ, qu\u00e9 dijiste\u2026\u2026?"}, {"tipo": "CHAR_TALK", "nombre": "", "texto": "Asuka pens\u00f3 que estaba escuchando cosas, as\u00ed que volvi\u00f3 a preguntar."}, {"tipo": "CHAR_TALK", "nombre": "", "texto": "Pero el temor de que ella realmente pudiera haber estado escuchando cosas le hac\u00eda emitir una voz muy tenue. Lo suficientemente silenciosa como para ser silenciada por el sonido del edificio derrumb\u00e1ndose."}, {"tipo": "VOICE_PLAY", "voz1": "voi_favor_c011_ore_0009", "voz2": ""}, {"tipo": "CHAR_TALK", "nombre": "Fuuma", "texto": "Dije gracias. As\u00ed que no me arrepiento de nada en caso de que muramos."}, {"tipo": "VOICE_PLAY", "voz1": "voi_favor_c011_ore_0010", "voz2": ""}, {"tipo": "CHAR_TALK", "nombre": "Fuuma", "texto": "\u00a1Gracias Asuka, todos los dem\u00e1s pudieron sobrevivir gracias a ti!"}, {"tipo": "CHAR_TALK", "nombre": "", "texto": "Pero Fuuma escuch\u00f3 la respuesta de Asuka y luego le respondi\u00f3."}, {"tipo": "VOICE_PLAY", "voz1": "voi_favor_c011_ore_0011", "voz2": ""}, {"tipo": "CHAR_TALK", "nombre": "Fuuma", "texto": "Pero no voy a morir tan f\u00e1cilmente. \u00a1Asegur\u00e9monos de salir de aqu\u00ed vivos! \u00a1Juntos!"}, {"tipo": "VOICE_PLAY", "voz1": "voi_favor_c011_asuka_0019", "voz2": ""}, {"tipo": "CHAR_TALK", "nombre": "Asuka", "texto": "...... \u00a1Uhht! \u00a1Uhhk!"}, {"tipo": "CHAR_TALK", "nombre": "", "texto": "Asuka ya no pudo decir nada despu\u00e9s de sentir s\u00f3lo a trav\u00e9s de su voz, que pod\u00eda confiar en Fuuma."}, {"tipo": "CHAR_TALK", "nombre": "", "texto": "En cambio, asiente con la cabeza en respuesta para mostrar sus sentimientos."}, {"tipo": "TALK_OUT"}, {"tipo": "CLOSE"}], "bg_black": "images/webp/texture/bg_black.webp", "snd_bgm_story_004": "audio/ogg/snd_bgm_story_004.ogg", "voi_favor_c011_asuka_0000": "audio/ogg/voi_favor_c011_asuka_0000.ogg", "voi_favor_c011_ore_0000": "audio/ogg/voi_favor_c011_ore_0000.ogg", "voi_favor_c011_asuka_0001": "audio/ogg/voi_favor_c011_asuka_0001.ogg", "voi_favor_c011_ore_0001": "audio/ogg/voi_favor_c011_ore_0001.ogg", "voi_favor_c011_asuka_0002": "audio/ogg/voi_favor_c011_asuka_0002.ogg", "voi_favor_c011_asuka_0003": "audio/ogg/voi_favor_c011_asuka_0003.ogg", "voi_favor_c011_asuka_0004": "audio/ogg/voi_favor_c011_asuka_0004.ogg", "voi_favor_c011_ore_0002": "audio/ogg/voi_favor_c011_ore_0002.ogg", "voi_favor_c011_asuka_0005": "audio/ogg/voi_favor_c011_asuka_0005.ogg", "char_11_0": "images/webp/sprite/char_11_0.webp", "char_11_b": "images/webp/sprite/char_11_b.webp", "voi_favor_c011_asuka_0006": "audio/ogg/voi_favor_c011_asuka_0006.ogg", "snd_bgm_story_003": "audio/ogg/snd_bgm_story_003.ogg", "voi_favor_c011_asuka_0007": "audio/ogg/voi_favor_c011_asuka_0007.ogg", "char_11_a": "images/webp/sprite/char_11_a.webp", "voi_favor_c011_asuka_0008": "audio/ogg/voi_favor_c011_asuka_0008.ogg", "voi_favor_c011_asuka_0009": "audio/ogg/voi_favor_c011_asuka_0009.ogg", "snd_story_explosion01": "audio/ogg/snd_story_explosion01.ogg", "voi_favor_c011_asuka_0010": "audio/ogg/voi_favor_c011_asuka_0010.ogg", "snd_bgm_e_story_003": "audio/ogg/snd_bgm_e_story_003.ogg", "voi_favor_c011_asuka_0011": "audio/ogg/voi_favor_c011_asuka_0011.ogg", "voi_favor_c011_asuka_0012": "audio/ogg/voi_favor_c011_asuka_0012.ogg", "voi_favor_c011_ore_0003": "audio/ogg/voi_favor_c011_ore_0003.ogg", "char_11_d": "images/webp/sprite/char_11_d.webp", "voi_favor_c011_asuka_0013": "audio/ogg/voi_favor_c011_asuka_0013.ogg", "voi_favor_c011_ore_0004": "audio/ogg/voi_favor_c011_ore_0004.ogg", "voi_favor_c011_asuka_0014": "audio/ogg/voi_favor_c011_asuka_0014.ogg", "voi_favor_c011_ore_0005": "audio/ogg/voi_favor_c011_ore_0005.ogg", "snd_story_explosion03": "audio/ogg/snd_story_explosion03.ogg", "voi_favor_c011_asuka_0015": "audio/ogg/voi_favor_c011_asuka_0015.ogg", "voi_favor_c011_ore_0006": "audio/ogg/voi_favor_c011_ore_0006.ogg", "snd_story_explosion02": "audio/ogg/snd_story_explosion02.ogg", "snd_story_run01": "audio/ogg/snd_story_run01.ogg", "char_11_c": "images/webp/sprite/char_11_c.webp", "voi_favor_c011_asuka_0016": "audio/ogg/voi_favor_c011_asuka_0016.ogg", "voi_favor_c011_ore_0007": "audio/ogg/voi_favor_c011_ore_0007.ogg", "voi_favor_c011_asuka_0017": "audio/ogg/voi_favor_c011_asuka_0017.ogg", "voi_favor_c011_ore_0008": "audio/ogg/voi_favor_c011_ore_0008.ogg", "voi_favor_c011_asuka_0018": "audio/ogg/voi_favor_c011_asuka_0018.ogg", "voi_favor_c011_ore_0009": "audio/ogg/voi_favor_c011_ore_0009.ogg", "voi_favor_c011_ore_0010": "audio/ogg/voi_favor_c011_ore_0010.ogg", "voi_favor_c011_ore_0011": "audio/ogg/voi_favor_c011_ore_0011.ogg", "voi_favor_c011_asuka_0019": "audio/ogg/voi_favor_c011_asuka_0019.ogg"}