{"script_txt": [{"tipo": "SHOW"}, {"tipo": "TALK_IN"}, {"tipo": "BG_LOAD", "clase": "FADE_IN", "nombre": "ls_nc010a", "time": 0.4, "x_scal": 1.25, "y_scal": 0.938}, {"tipo": "VOICE_PLAY", "voz1": "voi_favor_s066_ore_0000", "voz2": ""}, {"tipo": "CHAR_TALK", "nombre": "Fuuma", "texto": "Es \u00e9sta la informante de Amahara..."}, {"tipo": "CHAR_TALK", "nombre": "", "texto": "Tragu\u00e9 saliva inconscientemente dentro de la mansi\u00f3n de estilo occidental de la que hab\u00eda recibido una invitaci\u00f3n."}, {"tipo": "CHAR_TALK", "nombre": "", "texto": "La que estaba en el centro de esta atm\u00f3sfera, que parec\u00eda estar vigilando, era la due\u00f1a de esa mansi\u00f3n, un demonio femenino llamado Furfur."}, {"tipo": "CHAR_TALK", "nombre": "", "texto": "Adem\u00e1s de su aspecto sexy, irradiaba energ\u00eda demon\u00edaca y la presi\u00f3n abrumadora de una persona h\u00e1bil."}, {"tipo": "CHAR_TALK", "nombre": "", "texto": "Furfur sonri\u00f3 un poco y abri\u00f3 la boca para hablar conmigo, fing\u00ed estar tranquilo en la superficie."}, {"tipo": "CHAR_TALK", "nombre_char": "prpr", "x_pos": 0.0, "y_pos": "-140", "nombre_image": "supporter_066_0"}, {"tipo": "CHAR_SCALE", "nombre_char": "prpr", "escala": 1.3}, {"tipo": "MOVE_TO", "nombre_char": "prpr", "x_pos": 0.0, "time": 0.0}, {"tipo": "CHAR_FADE", "nombre_char": "prpr", "tipo_fade": "FADE_IN", "x_pos": 0.0, "time": 0.2}, {"tipo": "VOICE_PLAY", "voz1": "voi_favor_s066_huruhuru_0000", "voz2": ""}, {"tipo": "CHAR_TALK", "nombre": "Furfur", "texto": "Has encontrado el camino hasta aqu\u00ed, capit\u00e1n de las Fuerzas Especiales, Fuuma Kotaro."}, {"tipo": "VOICE_PLAY", "voz1": "voi_favor_s066_ore_0001", "voz2": ""}, {"tipo": "CHAR_TALK", "nombre": "Fuuma", "texto": "......Ya sabes todo sobre m\u00ed. Como era de esperar de un informante."}, {"tipo": "VOICE_PLAY", "voz1": "voi_favor_s066_huruhuru_0001", "voz2": ""}, {"tipo": "CHAR_TALK", "nombre": "Furfur", "texto": "Huhu, me siento halagada por tu cumplido. Como es esperado, soy capaz de darte la informaci\u00f3n que deseas."}, {"tipo": "CHAR_TALK", "nombre": "", "texto": "Su tono era educado, pero entre l\u00edneas estaba diciendo \"lo s\u00e9 todo sobre ti\"."}, {"tipo": "CHAR_TALK", "nombre": "", "texto": "Sin embargo, para que yo venga a verla, ella deber\u00eda saber por lo menos eso."}, {"tipo": "VOICE_PLAY", "voz1": "voi_favor_s066_ore_0002", "voz2": ""}, {"tipo": "CHAR_TALK", "nombre": "Fuuma", "texto": "S\u00ed, por eso estoy aqu\u00ed. \u00bfQu\u00e9 debo hacer para que me lo digas?"}, {"tipo": "CHAR_TALK", "nombre": "", "texto": "He o\u00eddo que su informaci\u00f3n se puede comprar con dinero, pero en algunos casos hace diferentes peticiones."}, {"tipo": "VOICE_PLAY", "voz1": "voi_favor_s066_ore_0003", "voz2": ""}, {"tipo": "CHAR_TALK", "nombre": "Fuuma", "texto": "(He o\u00eddo que ella decide el precio mirando la apariencia de uno......)"}, {"tipo": "CHAR_TALK", "nombre": "", "texto": "Espero que no me maten. Pod\u00eda sentir que me debilitaba bajo la presi\u00f3n de negociar con alguien abrumadoramente fuerte."}, {"tipo": "CHAR_TALK", "nombre": "", "texto": "Furfur, que parec\u00eda ver a trav\u00e9s de m\u00ed, se acerc\u00f3 a m\u00ed lentamente."}, {"tipo": "VOICE_PLAY", "voz1": "voi_favor_s066_huruhuru_0002", "voz2": ""}, {"tipo": "CHAR_TALK", "nombre": "Furfur", "texto": "Hmm, s\u00ed, no aceptar\u00e9 dinero de ti. En cambio, \u00bfpodr\u00edas hacerme un favor?"}, {"tipo": "CHAR_TALK", "nombre": "", "texto": "Su encantadora voz me hizo cosquillas en los o\u00eddos."}, {"tipo": "CHAR_TALK", "nombre": "", "texto": "Su suave mano me llev\u00f3 a una habitaci\u00f3n."}, {"tipo": "SE_PLAY", "volumen": 1.0, "nombre": "snd_story_walking01", "loop": "SE", "extension": ".ogg"}, {"tipo": "MOVE_TO", "nombre_char": "prpr", "x_pos": 6.0, "time": 0.0}, {"tipo": "CHAR_FADE", "nombre_char": "prpr", "tipo_fade": "FADE_OUT", "x_pos": 6.0, "time": 0.0}, {"tipo": "BG_LOAD", "clase": "MOVE", "nombre": "bg_black", "time": 2.0, "x_scal": 1.25, "y_scal": 0.938, "efecto": "LEFT_RIGHT"}, {"tipo": "VOICE_PLAY", "voz1": "voi_favor_s066_huruhuru_0003", "voz2": ""}, {"tipo": "CHAR_TALK", "nombre": "Furfur", "texto": "Uuuh, un poco m\u00e1s fuerte all\u00ed......"}, {"tipo": "CHAR_TALK", "nombre": "", "texto": "La voz de Furfur reson\u00f3 en la habitaci\u00f3n."}, {"tipo": "VOICE_PLAY", "voz1": "voi_favor_s066_huruhuru_0004", "voz2": ""}, {"tipo": "CHAR_TALK", "nombre": "Furfur", "texto": "Huhu, se siente bien......\u266a"}, {"tipo": "CHAR_TALK", "nombre": "", "texto": "Su piel, que reaccionaba sensiblemente a mis movimientos, estaba h\u00fameda por el sudor. Su aroma sal\u00eda como un vapor de su cuerpo enrojecido."}, {"tipo": "CHAR_TALK", "nombre": "", "texto": "Su cuerpo que se mov\u00eda seductoramente era sensible, as\u00ed que incluso con mi t\u00e9cnica pobre se calent\u00f3 r\u00e1pidamente."}, {"tipo": "VOICE_PLAY", "voz1": "voi_favor_s066_huruhuru_0005", "voz2": ""}, {"tipo": "CHAR_TALK", "nombre": "Furfur", "texto": "Aaaah......\u266a Aaa\u2026 all\u00ed, se siente incre\u00edble \u266a"}, {"tipo": "BG_LOAD", "clase": "MOVE", "nombre": "supporter_066_0", "time": 2.0, "x_scal": 1.0, "y_scal": 1.0, "efecto": "LEFT_RIGHT"}, {"tipo": "VOICE_PLAY", "voz1": "voi_favor_s066_ore_0004", "voz2": ""}, {"tipo": "CHAR_TALK", "nombre": "Fuuma", "texto": "Ejem\u2026 Se\u00f1orita \u00bfTodav\u00eda tengo que continuar......"}, {"tipo": "CHAR_TALK", "nombre": "", "texto": "Mientras masajeaba la espalda de Furfur, quien dejaba escapar ruidos sensuales, utilic\u00e9 inconscientemente los honor\u00edficos."}, {"tipo": "CHAR_TALK", "nombre": "", "texto": "Estaba nervioso y me preguntaba qu\u00e9 tipo de petici\u00f3n ten\u00eda para m\u00ed cuando se quit\u00f3 el vestido delante de m\u00ed. Resulta que quer\u00eda un masaje de cuerpo entero."}, {"tipo": "VOICE_PLAY", "voz1": "voi_favor_s066_huruhuru_0006", "voz2": ""}, {"tipo": "CHAR_TALK", "nombre": "Furfur", "texto": "\u00bfPero si acabamos de empezar? Si te detienes ahora, no te dir\u00e9 nada\u2026"}, {"tipo": "CHAR_TALK", "nombre": "", "texto": "Tumbada con la cara hacia abajo, Furfur r\u00e1pidamente rechaz\u00f3 mi petici\u00f3n."}, {"tipo": "CHAR_TALK", "nombre": "", "texto": "Al principio, tem\u00ed que hubiera alg\u00fan tipo de motivo oculto, pero realmente s\u00f3lo quer\u00eda un masaje. Bajo mis dedos, su cuerpo se relaj\u00f3 completamente, rindi\u00e9ndose a m\u00ed."}, {"tipo": "VOICE_PLAY", "voz1": "voi_favor_s066_huruhuru_0007", "voz2": ""}, {"tipo": "CHAR_TALK", "nombre": "Furfur", "texto": "Un masaje de una hora de un profesional no es tan caro. \u00bfCu\u00e1nto crees que vale mi informaci\u00f3n si se convierte en dinero?"}, {"tipo": "VOICE_PLAY", "voz1": "voi_favor_s066_ore_0005", "voz2": ""}, {"tipo": "CHAR_TALK", "nombre": "Fuuma", "texto": "Ugh...... Bueno, soy un aficionado, y entiendo que si este es el precio de la informaci\u00f3n, es barato......"}, {"tipo": "CHAR_TALK", "nombre": "", "texto": "Debido a que se relaj\u00f3 tanto, me volv\u00ed consciente de su cuerpo bajo mis manos."}, {"tipo": "CHAR_TALK", "nombre": "", "texto": "Aunque seas consciente de que est\u00e1s tratando con un demonio, sus cuerpos no son tan diferentes a los de los humanos."}, {"tipo": "CHAR_TALK", "nombre": "", "texto": "Con una gran toalla colocada sobre su espalda, las partes importantes estaban cubiertas, pero esa vista segu\u00eda siendo m\u00e1s que suficiente para estimularme."}, {"tipo": "VOICE_PLAY", "voz1": "voi_favor_s066_huruhuru_0008", "voz2": ""}, {"tipo": "CHAR_TALK", "nombre": "Furfur", "texto": "Oh, s\u00ed...... Como era de esperar, las manos firmes de un hombre son las mejores para un masaje eficaz. Siento que mis hombros se aflojaron."}, {"tipo": "CHAR_TALK", "nombre": "", "texto": "Lo que m\u00e1s me molestaba eran los dulces suspiros de Furfur."}, {"tipo": "CHAR_TALK", "nombre": "", "texto": "S\u00f3lo estaba masajeando sus hombros, pero sent\u00ed que estaba haciendo algo que no deb\u00eda."}, {"tipo": "CHAR_TALK", "nombre": "", "texto": "La expresi\u00f3n de Furfur era algo juguetona, as\u00ed que me pregunt\u00e9 si est\u00e1 viendo a trav\u00e9s de mi vacilaci\u00f3n."}, {"tipo": "VOICE_PLAY", "voz1": "voi_favor_s066_huruhuru_0009", "voz2": ""}, {"tipo": "CHAR_TALK", "nombre": "Furfur", "texto": "S\u00ed, siento que mis hombros est\u00e1n relajados ahora. \u00bfTe importar\u00eda masajearme la espalda ahora?"}, {"tipo": "VOICE_PLAY", "voz1": "voi_favor_s066_ore_0006", "voz2": ""}, {"tipo": "CHAR_TALK", "nombre": "Fuuma", "texto": "\u00bfLa espalda? \u00bfEst\u00e1 bien......?"}, {"tipo": "CHAR_TALK", "nombre": "", "texto": "Furfur me dio una orden que me pon\u00eda a prueba mientras vacilaba entre la raz\u00f3n y el deseo."}, {"tipo": "CHAR_TALK", "nombre": "", "texto": "Al verme obligado a tocar la espalda de Furfur, lo hice con vacilaci\u00f3n, pregunt\u00e1ndome si pod\u00eda ser realmente la de un demonio ya que su piel era realmente suave."}, {"tipo": "VOICE_PLAY", "voz1": "voi_favor_s066_huruhuru_0010", "voz2": ""}, {"tipo": "CHAR_TALK", "nombre": "Furfur", "texto": "S\u00ed, bueno...... no puedo llegar a esas partes por m\u00ed misma as\u00ed que, ah, hnnngh, se siente bien......"}, {"tipo": "CHAR_TALK", "nombre": "", "texto": "Su reacci\u00f3n fue claramente diferente a la de cuando le masaje\u00e9 los hombros."}, {"tipo": "CHAR_TALK", "nombre": "", "texto": "Ahora no s\u00f3lo suspiraba, sino que tambi\u00e9n retorc\u00eda su cuerpo y se estremec\u00eda de vez en cuando."}, {"tipo": "CHAR_TALK", "nombre": "", "texto": "Aunque estaba dudando, sus suspiros me hicieron querer intentar obtener m\u00e1s reacciones de ella."}, {"tipo": "VOICE_PLAY", "voz1": "voi_favor_s066_ore_0007", "voz2": ""}, {"tipo": "CHAR_TALK", "nombre": "Fuuma", "texto": "\u00bfDe verdad...? \u00bfQu\u00e9 tal, as\u00ed?"}, {"tipo": "VOICE_PLAY", "voz1": "voi_favor_s066_huruhuru_0011", "voz2": ""}, {"tipo": "CHAR_TALK", "nombre": "Furfur", "texto": "Aaaah, eso se siente bien \u266a Ooh, ah, est\u00e1 bien ir un poco duro, eh."}, {"tipo": "VOICE_PLAY", "voz1": "voi_favor_s066_ore_0008", "voz2": ""}, {"tipo": "CHAR_TALK", "nombre": "Fuuma", "texto": "Un poco m\u00e1s fuerte, huh...... \u00bfC-como as\u00ed?"}, {"tipo": "VOICE_PLAY", "voz1": "voi_favor_s066_huruhuru_0012", "voz2": ""}, {"tipo": "CHAR_TALK", "nombre": "Furfur", "texto": "Owh, siiiii, huuh, eso es incre\u00edble......\u266a Uah, por favor hazlo en toda, toda la espalda..."}, {"tipo": "CHAR_TALK", "nombre": "", "texto": "Cuanto m\u00e1s fuerte era el masaje, m\u00e1s reaccionaba ella."}, {"tipo": "CHAR_TALK", "nombre": "", "texto": "Sus suaves movimientos bajo la toalla se parec\u00edan m\u00e1s a los de un gato que a los de un humano."}, {"tipo": "CHAR_TALK", "nombre": "", "texto": "Aunque dud\u00e9, no pude parar porque sus reacciones eran de otro mundo."}, {"tipo": "CHAR_TALK", "nombre": "", "texto": "Las peticiones de Furfur no cesaron."}, {"tipo": "VOICE_PLAY", "voz1": "voi_favor_s066_huruhuru_0013", "voz2": ""}, {"tipo": "CHAR_TALK", "nombre": "Furfur", "texto": "Aah, me siento tan bien...... Por favor, masajea empezando por la cintura, hasta arriba."}, {"tipo": "VOICE_PLAY", "voz1": "voi_favor_s066_ore_0009", "voz2": ""}, {"tipo": "CHAR_TALK", "nombre": "Fuuma", "texto": "La cintura, entonces desde aqu\u00ed, \u00bfno?"}, {"tipo": "VOICE_PLAY", "voz1": "voi_favor_s066_huruhuru_0014", "voz2": ""}, {"tipo": "CHAR_TALK", "nombre": "Furfur", "texto": "Un poco m\u00e1s abajo, uhh\u2026 eso sigue siendo mi espalda\u2026"}, {"tipo": "CHAR_TALK", "nombre": "", "texto": "Ahora hab\u00eda requisitos sobre d\u00f3nde deb\u00eda tocarla."}, {"tipo": "CHAR_TALK", "nombre": "", "texto": "Me dio un poco de p\u00e1nico, pero fui m\u00e1s abajo. La piel all\u00ed era suave de una manera diferente en comparaci\u00f3n con la cintura."}, {"tipo": "VOICE_PLAY", "voz1": "voi_favor_s066_ore_0010", "voz2": ""}, {"tipo": "CHAR_TALK", "nombre": "Fuuma", "texto": "(T-esto no es su cintura, \u00bfes su trasero\u2500\u2500?)"}, {"tipo": "CHAR_TALK", "nombre": "", "texto": "No pude estar seguro porque esa parte estaba cubierta con la toalla, pero al mismo tiempo eso hac\u00eda que mi imaginaci\u00f3n volase."}, {"tipo": "CHAR_TALK", "nombre": "", "texto": "Para confirmar qu\u00e9 parte estaba tocando, acarici\u00e9 por ah\u00ed con un poco m\u00e1s de presi\u00f3n en las yemas de mis dedos."}, {"tipo": "VOICE_PLAY", "voz1": "voi_favor_s066_huruhuru_0015", "voz2": ""}, {"tipo": "CHAR_TALK", "nombre": "Furfur", "texto": "Huhu, este es un masaje bastante atrevido y sorprendente para un principiante \u266a Pens\u00e9 que eras inexperto con las mujeres, pero supongo que estaba equivocada \u266a"}, {"tipo": "VOICE_PLAY", "voz1": "voi_favor_s066_ore_0011", "voz2": ""}, {"tipo": "CHAR_TALK", "nombre": "Fuuma", "texto": "\u00a1\u00bfQu\u00e9?! Ah, no, que dices......"}, {"tipo": "VOICE_PLAY", "voz1": "voi_favor_s066_huruhuru_0016", "voz2": ""}, {"tipo": "CHAR_TALK", "nombre": "Furfur", "texto": "Uhuhu, s\u00f3lo estaba bromeando \u00bfO es este, eh, un tema sensible para ti?"}, {"tipo": "CHAR_TALK", "nombre": "", "texto": "Furfur est\u00e1 claramente disfrutando de mi reacci\u00f3n."}, {"tipo": "CHAR_TALK", "nombre": "", "texto": "Si esto continuaba, podr\u00eda perder la cabeza."}, {"tipo": "VOICE_PLAY", "voz1": "voi_favor_s066_ore_0012", "voz2": ""}, {"tipo": "CHAR_TALK", "nombre": "Fuuma", "texto": "\u00bfHe... he estado d\u00e1ndote un masaje durante 30 minutos? \u00bfNo ser\u00eda esto suficiente......?"}, {"tipo": "VOICE_PLAY", "voz1": "voi_favor_s066_huruhuru_0017", "voz2": ""}, {"tipo": "CHAR_TALK", "nombre": "Furfur", "texto": "\u00bfDe qu\u00e9 est\u00e1s hablando? S\u00f3lo me has masajeado los hombros y la espalda, todav\u00eda hay muchos lugares que necesitan relajarse."}, {"tipo": "VOICE_PLAY", "voz1": "voi_favor_s066_ore_0013", "voz2": ""}, {"tipo": "CHAR_TALK", "nombre": "Fuuma", "texto": "Ah, n-no, quiero decir, \u00bfes buena idea masajearte las otras partes...?"}, {"tipo": "VOICE_PLAY", "voz1": "voi_favor_s066_huruhuru_0018", "voz2": ""}, {"tipo": "CHAR_TALK", "nombre": "Furfur", "texto": "Te ped\u00ed que me dieras un masaje que equivaliera el precio de mi informaci\u00f3n, y ahora me dices que simplemente te la ceda, \u00bfcu\u00e1ndo ni siquiera me has pagado el precio completo?"}, {"tipo": "CHAR_TALK", "nombre": "", "texto": "dijo Furfur mientras sonr\u00eda, pero toda su aura indicaba que no escuchar\u00eda contraargumentos."}, {"tipo": "CHAR_TALK", "nombre": "", "texto": "Bajo esa presi\u00f3n no tuve m\u00e1s remedio que seguir moviendo las manos."}, {"tipo": "VOICE_PLAY", "voz1": "voi_favor_s066_huruhuru_0019", "voz2": ""}, {"tipo": "CHAR_TALK", "nombre": "Furfur", "texto": "As\u00ed es como me gusta. Uhuh, ahora un poco a los lados por favor \u266a"}, {"tipo": "VOICE_PLAY", "voz1": "voi_favor_s066_ore_0014", "voz2": ""}, {"tipo": "CHAR_TALK", "nombre": "Fuuma", "texto": "(\u00a1Hago esto por la informaci\u00f3n......! \u00a1Por la informaci\u00f3n......!)"}, {"tipo": "CHAR_TALK", "nombre": "", "texto": "Pens\u00e9 como si estuviera inventando excusas para poder seguir sirviendo a Furfur."}, {"tipo": "BG_LOAD", "clase": "MOVE", "nombre": "bg_black", "time": 2.0, "x_scal": 1.25, "y_scal": 0.938, "efecto": "LEFT_RIGHT"}, {"tipo": "VOICE_PLAY", "voz1": "voi_favor_s066_huruhuru_0020", "voz2": ""}, {"tipo": "CHAR_TALK", "nombre": "Furfur", "texto": "Huu...... Eso fue un masaje realmente bueno \u266a"}, {"tipo": "VOICE_PLAY", "voz1": "voi_favor_s066_ore_0015", "voz2": ""}, {"tipo": "CHAR_TALK", "nombre": "Fuuma", "texto": "En S-Serio...... Qu\u00e9 alivio..."}, {"tipo": "CHAR_TALK", "nombre": "", "texto": "Para cuando me permiti\u00f3 parar, la hab\u00eda masajeado durante dos horas."}, {"tipo": "CHAR_TALK", "nombre": "", "texto": "Tanto mi mente como mi cuerpo estaban abrumadoramente fatigados cuando Furfur me entreg\u00f3 su informaci\u00f3n."}, {"tipo": "CHAR_TALK", "nombre": "", "texto": "El contenido se\u00f1alaba exactamente lo que quer\u00edamos saber. Sus habilidades me provocaron escalofr\u00edos."}, {"tipo": "VOICE_PLAY", "voz1": "voi_favor_s066_huruhuru_0021", "voz2": ""}, {"tipo": "CHAR_TALK", "nombre": "Furfur", "texto": "Huhu, creo que ambos quedamos satisfechos. Espero que sigas utilizando mis servicios\u2500\u2500. \u00bfLa pr\u00f3xima vez tambi\u00e9n puedo pedir un masaje como pago?"}, {"tipo": "VOICE_PLAY", "voz1": "voi_favor_s066_ore_0016", "voz2": ""}, {"tipo": "CHAR_TALK", "nombre": "Fuuma", "texto": "Eh, por favor, cualquier otra cosa......"}, {"tipo": "CHAR_TALK", "nombre": "", "texto": "Furfur se ri\u00f3 a carcajadas mientras yo me desplomaba en el suelo."}, {"tipo": "TALK_OUT"}, {"tipo": "CLOSE"}], "ls_nc010a": "images/webp/texture/ls_nc010a.webp", "voi_favor_s066_ore_0000": "audio/ogg/voi_favor_s066_ore_0000.ogg", "supporter_066_0": "images/webp/sprite/supporter_066_0.webp", "voi_favor_s066_huruhuru_0000": "audio/ogg/voi_favor_s066_huruhuru_0000.ogg", "voi_favor_s066_ore_0001": "audio/ogg/voi_favor_s066_ore_0001.ogg", "voi_favor_s066_huruhuru_0001": "audio/ogg/voi_favor_s066_huruhuru_0001.ogg", "voi_favor_s066_ore_0002": "audio/ogg/voi_favor_s066_ore_0002.ogg", "voi_favor_s066_ore_0003": "audio/ogg/voi_favor_s066_ore_0003.ogg", "voi_favor_s066_huruhuru_0002": "audio/ogg/voi_favor_s066_huruhuru_0002.ogg", "snd_story_walking01": "audio/ogg/snd_story_walking01.ogg", "bg_black": "images/webp/texture/bg_black.webp", "voi_favor_s066_huruhuru_0003": "audio/ogg/voi_favor_s066_huruhuru_0003.ogg", "voi_favor_s066_huruhuru_0004": "audio/ogg/voi_favor_s066_huruhuru_0004.ogg", "voi_favor_s066_huruhuru_0005": "audio/ogg/voi_favor_s066_huruhuru_0005.ogg", "voi_favor_s066_ore_0004": "audio/ogg/voi_favor_s066_ore_0004.ogg", "voi_favor_s066_huruhuru_0006": "audio/ogg/voi_favor_s066_huruhuru_0006.ogg", "voi_favor_s066_huruhuru_0007": "audio/ogg/voi_favor_s066_huruhuru_0007.ogg", "voi_favor_s066_ore_0005": "audio/ogg/voi_favor_s066_ore_0005.ogg", "voi_favor_s066_huruhuru_0008": "audio/ogg/voi_favor_s066_huruhuru_0008.ogg", "voi_favor_s066_huruhuru_0009": "audio/ogg/voi_favor_s066_huruhuru_0009.ogg", "voi_favor_s066_ore_0006": "audio/ogg/voi_favor_s066_ore_0006.ogg", "voi_favor_s066_huruhuru_0010": "audio/ogg/voi_favor_s066_huruhuru_0010.ogg", "voi_favor_s066_ore_0007": "audio/ogg/voi_favor_s066_ore_0007.ogg", "voi_favor_s066_huruhuru_0011": "audio/ogg/voi_favor_s066_huruhuru_0011.ogg", "voi_favor_s066_ore_0008": "audio/ogg/voi_favor_s066_ore_0008.ogg", "voi_favor_s066_huruhuru_0012": "audio/ogg/voi_favor_s066_huruhuru_0012.ogg", "voi_favor_s066_huruhuru_0013": "audio/ogg/voi_favor_s066_huruhuru_0013.ogg", "voi_favor_s066_ore_0009": "audio/ogg/voi_favor_s066_ore_0009.ogg", "voi_favor_s066_huruhuru_0014": "audio/ogg/voi_favor_s066_huruhuru_0014.ogg", "voi_favor_s066_ore_0010": "audio/ogg/voi_favor_s066_ore_0010.ogg", "voi_favor_s066_huruhuru_0015": "audio/ogg/voi_favor_s066_huruhuru_0015.ogg", "voi_favor_s066_ore_0011": "audio/ogg/voi_favor_s066_ore_0011.ogg", "voi_favor_s066_huruhuru_0016": "audio/ogg/voi_favor_s066_huruhuru_0016.ogg", "voi_favor_s066_ore_0012": "audio/ogg/voi_favor_s066_ore_0012.ogg", "voi_favor_s066_huruhuru_0017": "audio/ogg/voi_favor_s066_huruhuru_0017.ogg", "voi_favor_s066_ore_0013": "audio/ogg/voi_favor_s066_ore_0013.ogg", "voi_favor_s066_huruhuru_0018": "audio/ogg/voi_favor_s066_huruhuru_0018.ogg", "voi_favor_s066_huruhuru_0019": "audio/ogg/voi_favor_s066_huruhuru_0019.ogg", "voi_favor_s066_ore_0014": "audio/ogg/voi_favor_s066_ore_0014.ogg", "voi_favor_s066_huruhuru_0020": "audio/ogg/voi_favor_s066_huruhuru_0020.ogg", "voi_favor_s066_ore_0015": "audio/ogg/voi_favor_s066_ore_0015.ogg", "voi_favor_s066_huruhuru_0021": "audio/ogg/voi_favor_s066_huruhuru_0021.ogg", "voi_favor_s066_ore_0016": "audio/ogg/voi_favor_s066_ore_0016.ogg"}